sql_buddy/__init__.py
sql_buddy/__main__.py
sql_buddy/concept.py
sql_buddy/create_objects.py
sql_buddy/sql_resources.py
sql_buddy/tx_deathrow_full.csv
sql_buddy-1.0.4.dist-info/LICENSE
sql_buddy-1.0.4.dist-info/METADATA
sql_buddy-1.0.4.dist-info/WHEEL
sql_buddy-1.0.4.dist-info/entry_points.txt
sql_buddy-1.0.4.dist-info/top_level.txt
sql_buddy-1.0.4.dist-info/RECORD
