Metadata-Version: 2.1
Name: sql-buddy
Version: 1.0.4
Summary: SQL study aid for the command line built with Python
Home-page: https://github.com/Captmoonshot/sql-buddy
Author: Sammy Lee
Author-email: sam@gygantor.com
License: MIT
Platform: UNKNOWN
Classifier: License :: OSI Approved :: MIT License
Classifier: Programming Language :: Python :: 3
Classifier: Programming Language :: Python :: 3.7
Requires-Dist: prompt-toolkit (==3.0.7)
Requires-Dist: Pygments (==2.7.1)
Requires-Dist: sqlalchemy (==1.3.19)
Requires-Dist: sqlalchemy-utils (==0.36.6)
